mowidget/__init__.py
mowidget/base/__init__.py
mowidget/base/dummy.py
mowidget/base/string_form.py
mowidget/design/__init__.py
mowidget/design/color_matrix.py
mowidget/design/color_picker.py
mowidget/frontend/css/array-viewer.css
mowidget/frontend/css/color-matrix.css
mowidget/frontend/css/color-picker.css
mowidget/frontend/css/dummy.css
mowidget/frontend/css/notebook-header.css
mowidget/frontend/css/pomodoro-timer.css
mowidget/frontend/css/string-form.css
mowidget/frontend/js/array-viewer.js
mowidget/frontend/js/color-matrix.js
mowidget/frontend/js/color-picker.js
mowidget/frontend/js/dummy.js
mowidget/frontend/js/notebook-header.js
mowidget/frontend/js/pomodoro-timer.js
mowidget/frontend/js/string-form.js
mowidget/layout/__init__.py
mowidget/layout/header.py
mowidget/productivity/__init__.py
mowidget/productivity/pomodoro_timer.py
mowidget/viewer/__init__.py
mowidget/viewer/array_viewer.py
mowidget-0.1.6.dist-info/METADATA
mowidget-0.1.6.dist-info/WHEEL
mowidget-0.1.6.dist-info/licenses/LICENSE
mowidget-0.1.6.dist-info/RECORD
